LICENSE
README.md
pyproject.toml
setup.py
src/aws_cloudwatch_log_minder/__init__.py
src/aws_cloudwatch_log_minder/__main__.py
src/aws_cloudwatch_log_minder/delete_empty_log_groups.py
src/aws_cloudwatch_log_minder/delete_empty_log_streams.py
src/aws_cloudwatch_log_minder/logger.py
src/aws_cloudwatch_log_minder/set_log_retention.py
src/aws_cloudwatch_log_minder.egg-info/PKG-INFO
src/aws_cloudwatch_log_minder.egg-info/SOURCES.txt
src/aws_cloudwatch_log_minder.egg-info/dependency_links.txt
src/aws_cloudwatch_log_minder.egg-info/entry_points.txt
src/aws_cloudwatch_log_minder.egg-info/not-zip-safe
src/aws_cloudwatch_log_minder.egg-info/requires.txt
src/aws_cloudwatch_log_minder.egg-info/top_level.txt