Metadata-Version: 2.1
Name: aws-cloudwatch-log-minder
Version: 0.5.3
Summary: Maintain AWS CloudWatch log streams
Home-page: https://github.com/binxio/aws-cloudwatch-log-minder
Author: Mark van Holsteijn
Author-email: mark@binx.io
License: BSD
Platform: any
Classifier: Development Status :: 4 - Beta
Classifier: Environment :: Console
Classifier: Intended Audience :: Developers
Classifier: License :: OSI Approved :: BSD License
Classifier: Operating System :: POSIX
Classifier: Operating System :: MacOS
Classifier: Operating System :: Unix
Classifier: Operating System :: Microsoft :: Windows
Classifier: Programming Language :: Python
Classifier: Programming Language :: Python :: 3
Classifier: Topic :: Software Development :: Libraries :: Python Modules
License-File: LICENSE
